veloxa/__init__.py
veloxa/cli.py
veloxa/templates/application_factory/config.py
veloxa/templates/application_factory/run.py
veloxa/templates/application_factory/app/__init__.py
veloxa/templates/application_factory/app/models.py
veloxa/templates/application_factory/app/routes.py
veloxa/templates/application_factory/app/__pycache__/__init__.cpython-313.pyc
veloxa/templates/application_factory/static/css/style.css
veloxa/templates/application_factory/static/images/favicon.svg
veloxa/templates/application_factory/static/images/veloxa.svg
veloxa/templates/application_factory/templates/index.html
veloxa/templates/basic_modular/app.py
veloxa/templates/basic_modular/templates/index.html
veloxa/templates/blueprint_based/run.py
veloxa/templates/blueprint_based/app/__init__.py
veloxa/templates/blueprint_based/app/auth/__init__.py
veloxa/templates/blueprint_based/app/auth/routes.py
veloxa/templates/blueprint_based/app/blog/__init__.py
veloxa/templates/blueprint_based/app/blog/routes.py
veloxa/templates/blueprint_based/static/css/style.css
veloxa/templates/blueprint_based/static/images/favicon.svg
veloxa/templates/blueprint_based/templates/index.html
veloxa/templates/factory_blueprints_config/config.py
veloxa/templates/factory_blueprints_config/requirements.txt
veloxa/templates/factory_blueprints_config/run.py
veloxa/templates/factory_blueprints_config/__pycache__/config.cpython-313.pyc
veloxa/templates/factory_blueprints_config/app/__init__.py
veloxa/templates/factory_blueprints_config/app/extensions.py
veloxa/templates/factory_blueprints_config/app/models.py
veloxa/templates/factory_blueprints_config/app/__pycache__/__init__.cpython-313.pyc
veloxa/templates/factory_blueprints_config/app/auth/__init__.py
veloxa/templates/factory_blueprints_config/app/auth/routes.py
veloxa/templates/factory_blueprints_config/app/auth/__pycache__/__init__.cpython-313.pyc
veloxa/templates/factory_blueprints_config/app/auth/__pycache__/routes.cpython-313.pyc
veloxa-0.6.0.dist-info/licenses/LICENSE
veloxa-0.6.0.dist-info/METADATA
veloxa-0.6.0.dist-info/WHEEL
veloxa-0.6.0.dist-info/entry_points.txt
veloxa-0.6.0.dist-info/top_level.txt
veloxa-0.6.0.dist-info/RECORD
