Metadata-Version: 2.4
Name: veloxa
Version: 0.6.0
Summary: A modern CLI tool to scaffold Flask project structures
Author-email: Yug Bhuva <yhuva817@gmail.com>
License: MIT
Project-URL: Homepage, https://github.com/yugbhuva/veloxa
Project-URL: Repository, https://github.com/yugbhuva/veloxa
Project-URL: Documentation, https://github.com/yugbhuva/veloxa#readme
Project-URL: Bug Tracker, https://github.com/yugbhuva/veloxa/issues
Keywords: flask,cli,scaffold,boilerplate,template,veloxa
Classifier: Development Status :: 3 - Alpha
Classifier: Intended Audience :: Developers
Classifier: License :: OSI Approved :: MIT License
Classifier: Operating System :: OS Independent
Classifier: Programming Language :: Python :: 3
Classifier: Programming Language :: Python :: 3.7
Classifier: Programming Language :: Python :: 3.8
Classifier: Programming Language :: Python :: 3.9
Classifier: Programming Language :: Python :: 3.10
Classifier: Programming Language :: Python :: 3.11
Classifier: Topic :: Software Development :: Code Generators
Classifier: Topic :: Software Development :: Libraries :: Python Modules
Classifier: Framework :: Flask
Requires-Python: >=3.7
License-File: LICENSE
Requires-Dist: questionary>=1.0.0
Dynamic: license-file
